tec/__init__.py
tec/ic/__init__.py
tec/ic/ia/__init__.py
tec/ic/ia/p2/g05.py
tec.ic.ia.p2.g05-4.0.0.dist-info/METADATA
tec.ic.ia.p2.g05-4.0.0.dist-info/RECORD
tec.ic.ia.p2.g05-4.0.0.dist-info/WHEEL
tec.ic.ia.p2.g05-4.0.0.dist-info/top_level.txt
