Metadata-Version: 2.1
Name: tec.ic.ia.p2.g05
Version: 4.0.0
Summary: g
Home-page: UNKNOWN
Author: JoseMora/DylanRodriguez/KarinaZeledon
Author-email: UNKNOWN
License: UNKNOWN
Requires-Dist: pandas (==0.19.1)
Requires-Dist: pyDatalog (==0.17.1)
